setup.py
Products/__init__.py
Products.ZScheduler.egg-info/PKG-INFO
Products.ZScheduler.egg-info/SOURCES.txt
Products.ZScheduler.egg-info/dependency_links.txt
Products.ZScheduler.egg-info/entry_points.txt
Products.ZScheduler.egg-info/namespace_packages.txt
Products.ZScheduler.egg-info/not-zip-safe
Products.ZScheduler.egg-info/requires.txt
Products.ZScheduler.egg-info/top_level.txt
Products/ZScheduler/Exceptions.py
Products/ZScheduler/FSZScheduleEvent.py
Products/ZScheduler/Log.py
Products/ZScheduler/Permissions.py
Products/ZScheduler/ZQueue.py
Products/ZScheduler/ZScheduleEvent.py
Products/ZScheduler/ZScheduler.py
Products/ZScheduler/__init__.py
Products/ZScheduler/config.py
Products/ZScheduler/tool.py
Products/ZScheduler/utils.py
Products/ZScheduler/Extensions/Install.py
Products/ZScheduler/Extensions/__init__.py
Products/ZScheduler/browser/__init__.py
Products/ZScheduler/browser/setup.py
Products/ZScheduler/browser/zscheduleevent.py
Products/ZScheduler/interfaces/IQueue.py
Products/ZScheduler/interfaces/ITimer.py
Products/ZScheduler/interfaces/__init__.py
Products/ZScheduler/tests/__init__.py
Products/ZScheduler/tests/testCrontab.py
Products/ZScheduler/tests/testDummy.py
Products/ZScheduler/tests/testFSScheduleEvent.py
Products/ZScheduler/tests/testScheduleEvent.py
Products/ZScheduler/tests/testTool.py
Products/ZScheduler/tests/testZCheck.py
Products/ZScheduler/tests/testZScheduler.py
Products/ZScheduler/tests/testZopeMultiThreaded.py
Products/ZScheduler/tests/testZopeSingleThreaded.py
Products/ZScheduler/timers/Base.py
Products/ZScheduler/timers/__init__.py
Products/ZScheduler/timers/Crontab/Crontab.py
Products/ZScheduler/timers/Crontab/__init__.py
Products/ZScheduler/timers/Dummy/Dummy.py
Products/ZScheduler/timers/Dummy/__init__.py
Products/ZScheduler/timers/ZopeMultiThreaded/ZopeMultiThreaded.py
Products/ZScheduler/timers/ZopeMultiThreaded/__init__.py
Products/ZScheduler/timers/ZopeSingleThreaded/ZopeSingleThreaded.py
Products/ZScheduler/timers/ZopeSingleThreaded/__init__.py