Metadata-Version: 1.1
Name: Products.ZScheduler
Version: 4.4.1
Summary: Zope/Plone remote timer
Home-page: http://www.last-bastion.net/forge/zscheduler
Author: Alan Milligan
Author-email: alan.milligan@last-bastion.net
License: GPL
Keywords: ZScheduler
Platform: UNKNOWN
Classifier: Framework :: Plone
Classifier: Programming Language :: Python
Classifier: Development Status :: 5 - Production/Stable
Classifier: License :: OSI Approved :: GNU General Public License (GPL)
